[
  {
    "description": "Message texture: gRedMessageXRightTex.i4",
    "confidence": 0.8,
    "tags": [
      "message",
      "texture",
      "ui",
      "i4_format"
    ],
    "analysis_method": "filename_pattern",
    "asset_name": "gRedMessageXRightTex.i4.png",
    "asset_path": "message_texture_static/gRedMessageXRightTex.i4.png",
    "analysis_timestamp": 1751816690.7924473
  },
  {
    "description": "Message texture: gRedMessageXLeftTex.i4",
    "confidence": 0.8,
    "tags": [
      "message",
      "texture",
      "ui",
      "i4_format"
    ],
    "analysis_method": "filename_pattern",
    "asset_name": "gRedMessageXLeftTex.i4.png",
    "asset_path": "message_texture_static/gRedMessageXLeftTex.i4.png",
    "analysis_timestamp": 1751816691.7928185
  },
  {
    "description": "Texture asset: gDungeonMapBlankFloorButtonTex.ia8",
    "confidence": 0.8,
    "tags": [
      "texture",
      "asset",
      "ia8_format"
    ],
    "analysis_method": "filename_pattern",
    "asset_name": "gDungeonMapBlankFloorButtonTex.ia8.png",
    "asset_path": "icon_item_dungeon_static/gDungeonMapBlankFloorButtonTex.ia8.png",
    "analysis_timestamp": 1751816692.7930841
  },
  {
    "description": "Texture asset: gDungeonMapLinkHeadTex.rgba16",
    "confidence": 0.8,
    "tags": [
      "texture",
      "asset",
      "rgba16_format"
    ],
    "analysis_method": "filename_pattern",
    "asset_name": "gDungeonMapLinkHeadTex.rgba16.png",
    "asset_path": "icon_item_dungeon_static/gDungeonMapLinkHeadTex.rgba16.png",
    "analysis_timestamp": 1751816693.7934144
  },
  {
    "description": "Texture asset: gDungeonMapB1ButtonTex.ia8",
    "confidence": 0.8,
    "tags": [
      "texture",
      "asset",
      "ia8_format"
    ],
    "analysis_method": "filename_pattern",
    "asset_name": "gDungeonMapB1ButtonTex.ia8.png",
    "asset_path": "icon_item_dungeon_static/gDungeonMapB1ButtonTex.ia8.png",
    "analysis_timestamp": 1751816694.7937708
  },
  {
    "description": "Texture asset: gDungeonMapSkullTex.rgba16",
    "confidence": 0.8,
    "tags": [
      "texture",
      "asset",
      "rgba16_format"
    ],
    "analysis_method": "filename_pattern",
    "asset_name": "gDungeonMapSkullTex.rgba16.png",
    "asset_path": "icon_item_dungeon_static/gDungeonMapSkullTex.rgba16.png",
    "analysis_timestamp": 1751816695.794058
  },
  {
    "description": "Texture asset: gDungeonMapB7ButtonTex.ia8",
    "confidence": 0.8,
    "tags": [
      "texture",
      "asset",
      "ia8_format"
    ],
    "analysis_method": "filename_pattern",
    "asset_name": "gDungeonMapB7ButtonTex.ia8.png",
    "asset_path": "icon_item_dungeon_static/gDungeonMapB7ButtonTex.ia8.png",
    "analysis_timestamp": 1751816696.7943048
  },
  {
    "description": "Texture asset: gDungeonMapB6ButtonTex.ia8",
    "confidence": 0.8,
    "tags": [
      "texture",
      "asset",
      "ia8_format"
    ],
    "analysis_method": "filename_pattern",
    "asset_name": "gDungeonMapB6ButtonTex.ia8.png",
    "asset_path": "icon_item_dungeon_static/gDungeonMapB6ButtonTex.ia8.png",
    "analysis_timestamp": 1751816697.7945814
  },
  {
    "description": "Texture asset: gDungeonMap6FButtonTex.ia8",
    "confidence": 0.8,
    "tags": [
      "texture",
      "asset",
      "ia8_format"
    ],
    "analysis_method": "filename_pattern",
    "asset_name": "gDungeonMap6FButtonTex.ia8.png",
    "asset_path": "icon_item_dungeon_static/gDungeonMap6FButtonTex.ia8.png",
    "analysis_timestamp": 1751816698.7949095
  },
  {
    "description": "Texture asset: gDungeonMap2FButtonTex.ia8",
    "confidence": 0.8,
    "tags": [
      "texture",
      "asset",
      "ia8_format"
    ],
    "analysis_method": "filename_pattern",
    "asset_name": "gDungeonMap2FButtonTex.ia8.png",
    "asset_path": "icon_item_dungeon_static/gDungeonMap2FButtonTex.ia8.png",
    "analysis_timestamp": 1751816699.795236
  },
  {
    "description": "Texture asset: gDungeonMap8FButtonTex.ia8",
    "confidence": 0.8,
    "tags": [
      "texture",
      "asset",
      "ia8_format"
    ],
    "analysis_method": "filename_pattern",
    "asset_name": "gDungeonMap8FButtonTex.ia8.png",
    "asset_path": "icon_item_dungeon_static/gDungeonMap8FButtonTex.ia8.png",
    "analysis_timestamp": 1751816700.7955854
  },
  {
    "description": "Texture asset: gDungeonMapB3ButtonTex.ia8",
    "confidence": 0.8,
    "tags": [
      "texture",
      "asset",
      "ia8_format"
    ],
    "analysis_method": "filename_pattern",
    "asset_name": "gDungeonMapB3ButtonTex.ia8.png",
    "asset_path": "icon_item_dungeon_static/gDungeonMapB3ButtonTex.ia8.png",
    "analysis_timestamp": 1751816701.795925
  },
  {
    "description": "Texture asset: gDungeonMap4FButtonTex.ia8",
    "confidence": 0.8,
    "tags": [
      "texture",
      "asset",
      "ia8_format"
    ],
    "analysis_method": "filename_pattern",
    "asset_name": "gDungeonMap4FButtonTex.ia8.png",
    "asset_path": "icon_item_dungeon_static/gDungeonMap4FButtonTex.ia8.png",
    "analysis_timestamp": 1751816702.7961934
  },
  {
    "description": "Texture asset: gDungeonMap3FButtonTex.ia8",
    "confidence": 0.8,
    "tags": [
      "texture",
      "asset",
      "ia8_format"
    ],
    "analysis_method": "filename_pattern",
    "asset_name": "gDungeonMap3FButtonTex.ia8.png",
    "asset_path": "icon_item_dungeon_static/gDungeonMap3FButtonTex.ia8.png",
    "analysis_timestamp": 1751816703.7965217
  },
  {
    "description": "Texture asset: gDungeonMapB8ButtonTex.ia8",
    "confidence": 0.8,
    "tags": [
      "texture",
      "asset",
      "ia8_format"
    ],
    "analysis_method": "filename_pattern",
    "asset_name": "gDungeonMapB8ButtonTex.ia8.png",
    "asset_path": "icon_item_dungeon_static/gDungeonMapB8ButtonTex.ia8.png",
    "analysis_timestamp": 1751816704.7968044
  },
  {
    "description": "Texture asset: gDungeonMap7FButtonTex.ia8",
    "confidence": 0.8,
    "tags": [
      "texture",
      "asset",
      "ia8_format"
    ],
    "analysis_method": "filename_pattern",
    "asset_name": "gDungeonMap7FButtonTex.ia8.png",
    "asset_path": "icon_item_dungeon_static/gDungeonMap7FButtonTex.ia8.png",
    "analysis_timestamp": 1751816705.7971275
  },
  {
    "description": "Texture asset: gDungeonMapB5ButtonTex.ia8",
    "confidence": 0.8,
    "tags": [
      "texture",
      "asset",
      "ia8_format"
    ],
    "analysis_method": "filename_pattern",
    "asset_name": "gDungeonMapB5ButtonTex.ia8.png",
    "asset_path": "icon_item_dungeon_static/gDungeonMapB5ButtonTex.ia8.png",
    "analysis_timestamp": 1751816706.7973936
  },
  {
    "description": "Texture asset: gDungeonMapB2ButtonTex.ia8",
    "confidence": 0.8,
    "tags": [
      "texture",
      "asset",
      "ia8_format"
    ],
    "analysis_method": "filename_pattern",
    "asset_name": "gDungeonMapB2ButtonTex.ia8.png",
    "asset_path": "icon_item_dungeon_static/gDungeonMapB2ButtonTex.ia8.png",
    "analysis_timestamp": 1751816707.7977145
  },
  {
    "description": "Texture asset: gDungeonMap1FButtonTex.ia8",
    "confidence": 0.8,
    "tags": [
      "texture",
      "asset",
      "ia8_format"
    ],
    "analysis_method": "filename_pattern",
    "asset_name": "gDungeonMap1FButtonTex.ia8.png",
    "asset_path": "icon_item_dungeon_static/gDungeonMap1FButtonTex.ia8.png",
    "analysis_timestamp": 1751816708.798047
  },
  {
    "description": "Texture asset: gDungeonMap5FButtonTex.ia8",
    "confidence": 0.8,
    "tags": [
      "texture",
      "asset",
      "ia8_format"
    ],
    "analysis_method": "filename_pattern",
    "asset_name": "gDungeonMap5FButtonTex.ia8.png",
    "asset_path": "icon_item_dungeon_static/gDungeonMap5FButtonTex.ia8.png",
    "analysis_timestamp": 1751816709.7983851
  },
  {
    "description": "Texture asset: gDungeonMapB4ButtonTex.ia8",
    "confidence": 0.8,
    "tags": [
      "texture",
      "asset",
      "ia8_format"
    ],
    "analysis_method": "filename_pattern",
    "asset_name": "gDungeonMapB4ButtonTex.ia8.png",
    "asset_path": "icon_item_dungeon_static/gDungeonMapB4ButtonTex.ia8.png",
    "analysis_timestamp": 1751816710.798756
  },
  {
    "description": "Nintendo logo texture: nintendo_rogo_static_000029C0_Tex.i8",
    "confidence": 0.8,
    "tags": [
      "logo",
      "nintendo",
      "branding"
    ],
    "analysis_method": "filename_pattern",
    "asset_name": "nintendo_rogo_static_000029C0_Tex.i8.png",
    "asset_path": "nintendo_rogo_static/nintendo_rogo_static_000029C0_Tex.i8.png",
    "analysis_timestamp": 1751816711.7990189
  },
  {
    "description": "Nintendo logo texture: nintendo_rogo_static_Tex_001800.i8",
    "confidence": 0.8,
    "tags": [
      "logo",
      "nintendo",
      "branding"
    ],
    "analysis_method": "filename_pattern",
    "asset_name": "nintendo_rogo_static_Tex_001800.i8.png",
    "asset_path": "nintendo_rogo_static/nintendo_rogo_static_Tex_001800.i8.png",
    "analysis_timestamp": 1751816712.7992618
  },
  {
    "description": "Nintendo logo texture: nintendo_rogo_static_Tex_000000.i8",
    "confidence": 0.8,
    "tags": [
      "logo",
      "nintendo",
      "branding"
    ],
    "analysis_method": "filename_pattern",
    "asset_name": "nintendo_rogo_static_Tex_000000.i8.png",
    "asset_path": "nintendo_rogo_static/nintendo_rogo_static_Tex_000000.i8.png",
    "analysis_timestamp": 1751816713.799514
  },
  {
    "error": "Image file not found"
  },
  {
    "description": "Texture asset: gQuestIconStoneOfAgonyTex.rgba32",
    "confidence": 0.8,
    "tags": [
      "texture",
      "asset"
    ],
    "analysis_method": "filename_pattern",
    "asset_name": "gQuestIconStoneOfAgonyTex.rgba32.png",
    "asset_path": "icon_item_24_static/gQuestIconStoneOfAgonyTex.rgba32.png",
    "analysis_timestamp": 1751816715.8000638
  },
  {
    "description": "Texture asset: gQuestIconMedallionFireTex.rgba32",
    "confidence": 0.8,
    "tags": [
      "texture",
      "asset"
    ],
    "analysis_method": "filename_pattern",
    "asset_name": "gQuestIconMedallionFireTex.rgba32.png",
    "asset_path": "icon_item_24_static/gQuestIconMedallionFireTex.rgba32.png",
    "analysis_timestamp": 1751816716.8004067
  },
  {
    "description": "Texture asset: gQuestIconDungeonMapTex.rgba32",
    "confidence": 0.8,
    "tags": [
      "texture",
      "asset"
    ],
    "analysis_method": "filename_pattern",
    "asset_name": "gQuestIconDungeonMapTex.rgba32.png",
    "asset_path": "icon_item_24_static/gQuestIconDungeonMapTex.rgba32.png",
    "analysis_timestamp": 1751816717.8006806
  },
  {
    "description": "Texture asset: gQuestIconGoldSkulltulaTex.rgba32",
    "confidence": 0.8,
    "tags": [
      "texture",
      "asset"
    ],
    "analysis_method": "filename_pattern",
    "asset_name": "gQuestIconGoldSkulltulaTex.rgba32.png",
    "asset_path": "icon_item_24_static/gQuestIconGoldSkulltulaTex.rgba32.png",
    "analysis_timestamp": 1751816718.804745
  },
  {
    "description": "Texture asset: gQuestIconHeartContainerTex.rgba32",
    "confidence": 0.8,
    "tags": [
      "texture",
      "asset"
    ],
    "analysis_method": "filename_pattern",
    "asset_name": "gQuestIconHeartContainerTex.rgba32.png",
    "asset_path": "icon_item_24_static/gQuestIconHeartContainerTex.rgba32.png",
    "analysis_timestamp": 1751816719.805079
  },
  {
    "description": "Texture asset: gQuestIconGerudosCardTex.rgba32",
    "confidence": 0.8,
    "tags": [
      "texture",
      "asset"
    ],
    "analysis_method": "filename_pattern",
    "asset_name": "gQuestIconGerudosCardTex.rgba32.png",
    "asset_path": "icon_item_24_static/gQuestIconGerudosCardTex.rgba32.png",
    "analysis_timestamp": 1751816720.805418
  },
  {
    "description": "Texture asset: gQuestIconMagicJarBigTex.rgba32",
    "confidence": 0.8,
    "tags": [
      "texture",
      "asset"
    ],
    "analysis_method": "filename_pattern",
    "asset_name": "gQuestIconMagicJarBigTex.rgba32.png",
    "asset_path": "icon_item_24_static/gQuestIconMagicJarBigTex.rgba32.png",
    "analysis_timestamp": 1751816721.8057725
  },
  {
    "description": "Texture asset: gQuestIconMedallionLightTex.rgba32",
    "confidence": 0.8,
    "tags": [
      "texture",
      "asset"
    ],
    "analysis_method": "filename_pattern",
    "asset_name": "gQuestIconMedallionLightTex.rgba32.png",
    "asset_path": "icon_item_24_static/gQuestIconMedallionLightTex.rgba32.png",
    "analysis_timestamp": 1751816722.8060412
  },
  {
    "description": "Texture asset: gQuestIconDungeonCompassTex.rgba32",
    "confidence": 0.8,
    "tags": [
      "texture",
      "asset"
    ],
    "analysis_method": "filename_pattern",
    "asset_name": "gQuestIconDungeonCompassTex.rgba32.png",
    "asset_path": "icon_item_24_static/gQuestIconDungeonCompassTex.rgba32.png",
    "analysis_timestamp": 1751816723.8063767
  },
  {
    "description": "Texture asset: gQuestIconHeartPieceTex.rgba32",
    "confidence": 0.8,
    "tags": [
      "texture",
      "asset"
    ],
    "analysis_method": "filename_pattern",
    "asset_name": "gQuestIconHeartPieceTex.rgba32.png",
    "asset_path": "icon_item_24_static/gQuestIconHeartPieceTex.rgba32.png",
    "analysis_timestamp": 1751816724.8066916
  },
  {
    "description": "Texture asset: gQuestIconKokiriEmeraldTex.rgba32",
    "confidence": 0.8,
    "tags": [
      "texture",
      "asset"
    ],
    "analysis_method": "filename_pattern",
    "asset_name": "gQuestIconKokiriEmeraldTex.rgba32.png",
    "asset_path": "icon_item_24_static/gQuestIconKokiriEmeraldTex.rgba32.png",
    "analysis_timestamp": 1751816725.8070147
  },
  {
    "description": "Texture asset: gQuestIconMagicJarSmallTex.rgba32",
    "confidence": 0.8,
    "tags": [
      "texture",
      "asset"
    ],
    "analysis_method": "filename_pattern",
    "asset_name": "gQuestIconMagicJarSmallTex.rgba32.png",
    "asset_path": "icon_item_24_static/gQuestIconMagicJarSmallTex.rgba32.png",
    "analysis_timestamp": 1751816726.8073595
  },
  {
    "description": "Texture asset: gQuestIconMedallionSpiritTex.rgba32",
    "confidence": 0.8,
    "tags": [
      "texture",
      "asset"
    ],
    "analysis_method": "filename_pattern",
    "asset_name": "gQuestIconMedallionSpiritTex.rgba32.png",
    "asset_path": "icon_item_24_static/gQuestIconMedallionSpiritTex.rgba32.png",
    "analysis_timestamp": 1751816727.807787
  },
  {
    "description": "Texture asset: gQuestIconMedallionWaterTex.rgba32",
    "confidence": 0.8,
    "tags": [
      "texture",
      "asset"
    ],
    "analysis_method": "filename_pattern",
    "asset_name": "gQuestIconMedallionWaterTex.rgba32.png",
    "asset_path": "icon_item_24_static/gQuestIconMedallionWaterTex.rgba32.png",
    "analysis_timestamp": 1751816728.8081295
  },
  {
    "description": "Texture asset: gQuestIconSmallKeyTex.rgba32",
    "confidence": 0.8,
    "tags": [
      "texture",
      "asset"
    ],
    "analysis_method": "filename_pattern",
    "asset_name": "gQuestIconSmallKeyTex.rgba32.png",
    "asset_path": "icon_item_24_static/gQuestIconSmallKeyTex.rgba32.png",
    "analysis_timestamp": 1751816729.8084664
  },
  {
    "description": "Texture asset: gQuestIconDungeonBossKeyTex.rgba32",
    "confidence": 0.8,
    "tags": [
      "texture",
      "asset"
    ],
    "analysis_method": "filename_pattern",
    "asset_name": "gQuestIconDungeonBossKeyTex.rgba32.png",
    "asset_path": "icon_item_24_static/gQuestIconDungeonBossKeyTex.rgba32.png",
    "analysis_timestamp": 1751816730.8088682
  },
  {
    "description": "Texture asset: gQuestIconZoraSapphireTex.rgba32",
    "confidence": 0.8,
    "tags": [
      "texture",
      "asset"
    ],
    "analysis_method": "filename_pattern",
    "asset_name": "gQuestIconZoraSapphireTex.rgba32.png",
    "asset_path": "icon_item_24_static/gQuestIconZoraSapphireTex.rgba32.png",
    "analysis_timestamp": 1751816731.8091288
  },
  {
    "description": "Texture asset: gQuestIconGoronRubyTex.rgba32",
    "confidence": 0.8,
    "tags": [
      "texture",
      "asset"
    ],
    "analysis_method": "filename_pattern",
    "asset_name": "gQuestIconGoronRubyTex.rgba32.png",
    "asset_path": "icon_item_24_static/gQuestIconGoronRubyTex.rgba32.png",
    "analysis_timestamp": 1751816732.8094182
  },
  {
    "description": "Texture asset: gQuestIconMedallionForestTex.rgba32",
    "confidence": 0.8,
    "tags": [
      "texture",
      "asset"
    ],
    "analysis_method": "filename_pattern",
    "asset_name": "gQuestIconMedallionForestTex.rgba32.png",
    "asset_path": "icon_item_24_static/gQuestIconMedallionForestTex.rgba32.png",
    "analysis_timestamp": 1751816733.8097606
  },
  {
    "description": "Texture asset: gQuestIconMedallionShadowTex.rgba32",
    "confidence": 0.8,
    "tags": [
      "texture",
      "asset"
    ],
    "analysis_method": "filename_pattern",
    "asset_name": "gQuestIconMedallionShadowTex.rgba32.png",
    "asset_path": "icon_item_24_static/gQuestIconMedallionShadowTex.rgba32.png",
    "analysis_timestamp": 1751816734.8101056
  },
  {
    "description": "Map name texture: gHyruleCastlePositionNameJPNTex.ia8",
    "confidence": 0.8,
    "tags": [
      "map_name",
      "text",
      "ui",
      "ia8_format"
    ],
    "analysis_method": "filename_pattern",
    "asset_name": "gHyruleCastlePositionNameJPNTex.ia8.png",
    "asset_path": "map_name_static/gHyruleCastlePositionNameJPNTex.ia8.png",
    "analysis_timestamp": 1751816735.8103855
  },
  {
    "description": "Map name texture: gHyruleFieldPointNameENGTex.ia4",
    "confidence": 0.8,
    "tags": [
      "map_name",
      "text",
      "ui"
    ],
    "analysis_method": "filename_pattern",
    "asset_name": "gHyruleFieldPointNameENGTex.ia4.png",
    "asset_path": "map_name_static/gHyruleFieldPointNameENGTex.ia4.png",
    "analysis_timestamp": 1751816736.8107495
  },
  {
    "description": "Map name texture: gHyliaLakesidePointNameJPNTex.ia4",
    "confidence": 0.8,
    "tags": [
      "map_name",
      "text",
      "ui"
    ],
    "analysis_method": "filename_pattern",
    "asset_name": "gHyliaLakesidePointNameJPNTex.ia4.png",
    "asset_path": "map_name_static/gHyliaLakesidePointNameJPNTex.ia4.png",
    "analysis_timestamp": 1751816737.8110204
  },
  {
    "description": "Map name texture: gHauntedWastelandPointNameENGTex.ia4",
    "confidence": 0.8,
    "tags": [
      "map_name",
      "text",
      "ui"
    ],
    "analysis_method": "filename_pattern",
    "asset_name": "gHauntedWastelandPointNameENGTex.ia4.png",
    "asset_path": "map_name_static/gHauntedWastelandPointNameENGTex.ia4.png",
    "analysis_timestamp": 1751816738.8113542
  },
  {
    "description": "Map name texture: gHauntedWastelandPointNameJPNTex.ia4",
    "confidence": 0.8,
    "tags": [
      "map_name",
      "text",
      "ui"
    ],
    "analysis_method": "filename_pattern",
    "asset_name": "gHauntedWastelandPointNameJPNTex.ia4.png",
    "asset_path": "map_name_static/gHauntedWastelandPointNameJPNTex.ia4.png",
    "analysis_timestamp": 1751816739.811716
  }
]